LICENSE
MANIFEST.in
README.md
setup.py
brewerydb/__init__.py
brewerydb/beer.py
brewerydb/brewery.py
brewerydb/brewerydb.py
brewerydb/exceptions.py
pybrewerydb.egg-info/PKG-INFO
pybrewerydb.egg-info/SOURCES.txt
pybrewerydb.egg-info/dependency_links.txt
pybrewerydb.egg-info/requires.txt
pybrewerydb.egg-info/top_level.txt
pybrewerydb.egg-info/zip-safe