Metadata-Version: 1.1
Name: pybrewerydb
Version: 0.1.4
Summary: Python wrapper for the BreweryDB API
Home-page: http://github.com/dstegelman/PyBreweryDB
Author: Derek Stegelman
Author-email: dstegelman@gmail.com
License: MIT
Keywords: beer brewerydb api python
Platform: UNKNOWN
Classifier: Development Status :: 1 - Planning
Classifier: Environment :: Console
Classifier: Intended Audience :: Developers
Classifier: Natural Language :: English
Classifier: Operating System :: OS Independent
Classifier: Programming Language :: Python
Classifier: Topic :: Internet :: WWW/HTTP :: Dynamic Content :: CGI Tools/Libraries
Classifier: Topic :: Utilities
Classifier: License :: OSI Approved :: MIT License
